beamer.py
beamer-0.2.0.dist-info/LICENSE
beamer-0.2.0.dist-info/METADATA
beamer-0.2.0.dist-info/WHEEL
beamer-0.2.0.dist-info/entry_points.txt
beamer-0.2.0.dist-info/top_level.txt
beamer-0.2.0.dist-info/RECORD
