Metadata-Version: 2.1
Name: beamer
Version: 0.2.0
Summary: Simplistic CLI for toggling and positioning a secondary monitor or projector
Home-page: https://github.com/philer/beamer
Author: Philipp Miller
Author-email: me@philer.org
License: MIT
Keywords: cli xrandr beamer mirror screen
Platform: UNKNOWN
Classifier: License :: OSI Approved :: MIT License
Classifier: Programming Language :: Python :: 3 :: Only
Classifier: Operating System :: POSIX :: Linux
Classifier: Topic :: Desktop Environment
Classifier: Topic :: Utilities
Classifier: Natural Language :: English
Requires-Python: >=3
